ticton/__init__.py
ticton/arithmetic.py
ticton/callbacks.py
ticton/client.py
ticton/decoder.py
ticton/parser.py
ticton-0.1.31.dist-info/LICENSE
ticton-0.1.31.dist-info/METADATA
ticton-0.1.31.dist-info/WHEEL
ticton-0.1.31.dist-info/RECORD
