Metadata-Version: 2.1
Name: ticton
Version: 0.1.31
Summary: 
Author: alan890104
Author-email: alan890104@gmail.com
Requires-Python: >=3.10,<3.12
Classifier: Programming Language :: Python :: 3
Classifier: Programming Language :: Python :: 3.10
Classifier: Programming Language :: Python :: 3.11
Requires-Dist: aiohttp (>=3.9.3,<4.0.0)
Requires-Dist: pytoncenter (==0.0.14)
Requires-Dist: tonpy (==0.0.0.1.2b0)
Requires-Dist: tonsdk (==1.0.13)
Requires-Dist: tvm-valuetypes (>=0.0.12,<0.0.13)
